everseed/__init__.py
everseed/everseed.py
everseed-0.0.2.dist-info/METADATA
everseed-0.0.2.dist-info/WHEEL
everseed-0.0.2.dist-info/licenses/LICENSE
everseed-0.0.2.dist-info/RECORD
